.gitignore
.travis.yml
AUTHORS
CHANGELOG.md
LICENSE
MANIFEST.in
README.md
qiproject.xml
run_wooqi_tests.sh
setup.cfg
setup.py
wooqi_pytest.py
testing/actions_functions.py
testing/conftest.py
testing/test_functions.py
testing/cache_feature/run_wooqi_cache_tests.sh
testing/cache_feature/actions/cache_loop_different_action.ini
testing/cache_feature/actions/cache_loop_same_action.ini
testing/cache_feature/actions/cache_required_action.ini
testing/cache_feature/actions/cache_required_action_with_uut.ini
testing/cache_feature/actions/cache_standard_action.ini
testing/cache_feature/actions/cache_uut_different_action.ini
testing/cache_feature/actions/cache_uut_same_action.ini
testing/cache_feature/tests/cache_loop_different_test.ini
testing/cache_feature/tests/cache_loop_same_test.ini
testing/cache_feature/tests/cache_loop_uut_different_test.ini
testing/cache_feature/tests/cache_loop_uut_same_test.ini
testing/cache_feature/tests/cache_required_test.ini
testing/cache_feature/tests/cache_required_test_with_uut.ini
testing/cache_feature/tests/cache_standard_test.ini
testing/cache_feature/tests/cache_uut_different_test.ini
testing/cache_feature/tests/cache_uut_same_test.ini
testing/loop_feature/run_wooqi_loop_tests.sh
testing/loop_feature/actions/loop_different_actions.ini
testing/loop_feature/actions/loop_mixed_actions.ini
testing/loop_feature/actions/loop_same_action.ini
testing/loop_feature/tests/loop_different_tests.ini
testing/loop_feature/tests/loop_different_tests_uut.ini
testing/loop_feature/tests/loop_mixed_tests.ini
testing/loop_feature/tests/loop_same_test.ini
testing/loop_feature/tests/loop_same_test_uut.ini
testing/postfail_feature/run_wooqi_postfail_tests.sh
testing/postfail_feature/actions/postfail_next_step.ini
testing/postfail_feature/actions/postfail_next_step_same_action.ini
testing/postfail_feature/actions/postfail_other_action.ini
testing/postfail_feature/actions/postfail_other_action_same_action.ini
wooqi.egg-info/PKG-INFO
wooqi.egg-info/SOURCES.txt
wooqi.egg-info/dependency_links.txt
wooqi.egg-info/entry_points.txt
wooqi.egg-info/not-zip-safe
wooqi.egg-info/requires.txt
wooqi.egg-info/top_level.txt
