Metadata-Version: 2.1
Name: wooqi
Version: 2.0.1
Summary: Python module allowing to parametrize all a test sequence thanks to a config file
Home-page: https://github.com/aldebaran/wooqi
License: BSD-3
Download-URL: https://pypi.org/project/wooqi/
Platform: unix
Platform: linux
Platform: osx
Platform: cygwin
Platform: win32
